ammeter_fpn_4_24/__init__.py
ammeter_fpn_4_24/__main__.py
ammeter_fpn_4_24/backWorking.py
ammeter_fpn_4_24/chart.py
ammeter_fpn_4_24/dataHandler.py
ammeter_fpn_4_24/modbusRTUOverTCP.py
ammeter_fpn_4_24/model.py
ammeter_fpn_4_24/outputData.py
ammeter_fpn_4_24/tempCodeRunnerFile.py
ammeter_fpn_4_24/ui/__init__.py
ammeter_fpn_4_24/ui/dialogConfig.py
ammeter_fpn_4_24/ui/mainWindow.py
ammeter_fpn_4_24/ui/uic/__init__.py
ammeter_fpn_4_24/ui/uic/dialogconfig.ui
ammeter_fpn_4_24/ui/uic/mainwindow.ui
neofti_ammeter_fpn_4_24-0.0.5.dist-info/METADATA
neofti_ammeter_fpn_4_24-0.0.5.dist-info/WHEEL
neofti_ammeter_fpn_4_24-0.0.5.dist-info/entry_points.txt
neofti_ammeter_fpn_4_24-0.0.5.dist-info/top_level.txt
neofti_ammeter_fpn_4_24-0.0.5.dist-info/RECORD
